fdrepl/__init__.py
fdrepl/repl.py
fdrepl-0.1.0.dist-info/LICENSE
fdrepl-0.1.0.dist-info/METADATA
fdrepl-0.1.0.dist-info/WHEEL
fdrepl-0.1.0.dist-info/entry_points.txt
fdrepl-0.1.0.dist-info/RECORD
