Metadata-Version: 2.1
Name: fdrepl
Version: 0.1.0
Summary: REPL for interacting with functional dependencies, their closures, and levels of normalization.
License: BSD-3-Clause
Author: Gabe Fierro
Author-email: gtfierro@mines.edu
Requires-Python: >=3.11,<4.0
Classifier: License :: OSI Approved :: BSD License
Classifier: Programming Language :: Python :: 3
Classifier: Programming Language :: Python :: 3.11
Requires-Dist: colorama (>=0.4.6,<0.5.0)
